data_guardian/__init__.py
data_guardian/cli.py
data_guardian/analysis/__init__.py
data_guardian/analysis/constant_columns.py
data_guardian/analysis/data_types.py
data_guardian/analysis/duplicated_rows.py
data_guardian/analysis/missing_values.py
data_guardian/analysis/outliers.py
data_guardian/analysis/string_patterns.py
data_guardian/core/DataIssue.py
data_guardian/core/DatasetProfile.py
data_guardian/core/QualityScore.py
data_guardian/core/__init__.py
data_guardian/io/__init__.py
data_guardian/io/loaders.py
data_guardian/reporting/__init__.py
data_guardian/reporting/html_reporter.py
data_guardian/reporting/pdf_reporter.py
data_guardian/reporting/templates/report_template.html
data_guardian-0.1.0.dist-info/licenses/LICENSE
data_guardian-0.1.0.dist-info/METADATA
data_guardian-0.1.0.dist-info/WHEEL
data_guardian-0.1.0.dist-info/entry_points.txt
data_guardian-0.1.0.dist-info/top_level.txt
data_guardian-0.1.0.dist-info/RECORD
