Metadata-Version: 2.4
Name: data-guardian
Version: 0.1.0
Summary: A Python library for comprehensive data quality analysis and reporting on tabular datasets.
Author-email: Saad Fikri <fsaad1929@gmail.com>
License: MIT License
Project-URL: Homepage, https://github.com/SAAD2003D/data-guardian
Project-URL: Bug-Tracker, https://github.com/yourusername/data-guardian/issues
Keywords: data quality,data analysis,pandas,data cleaning,data profiling,ETL
Classifier: Development Status :: 3 - Alpha
Classifier: Intended Audience :: Developers
Classifier: Intended Audience :: Science/Research
Classifier: Intended Audience :: System Administrators
Classifier: License :: OSI Approved :: MIT License
Classifier: Programming Language :: Python :: 3
Classifier: Programming Language :: Python :: 3.8
Classifier: Programming Language :: Python :: 3.9
Classifier: Programming Language :: Python :: 3.10
Classifier: Programming Language :: Python :: 3.11
Classifier: Operating System :: OS Independent
Classifier: Topic :: Scientific/Engineering :: Information Analysis
Classifier: Topic :: Software Development :: Libraries :: Python Modules
Classifier: Topic :: Utilities
Requires-Python: >=3.10.9
License-File: LICENSE
Requires-Dist: pandas>=1.3
Requires-Dist: numpy>=1.20
Requires-Dist: openpyxl>=3.0
Requires-Dist: Jinja2>=3.0
Requires-Dist: xhtml2pdf>=0.2.5
Dynamic: license-file
